src/__init__.py
src/db/__init__.py
src/db/config.py
src/db/user.py
src/utility/__init__.py
src/utility/logging.py
TPLUtils-0.0.1.dist-info/METADATA
TPLUtils-0.0.1.dist-info/WHEEL
TPLUtils-0.0.1.dist-info/top_level.txt
TPLUtils-0.0.1.dist-info/RECORD
