Metadata-Version: 2.1
Name: TPLUtils
Version: 0.0.1
Summary: A package used for the TPL project
Home-page: https://github.com/The-Programming-Lab/TPL_package
Author: The Programming Lab
Author-email: braeden.norman6@gmail.com
License: MIT
Requires-Dist: fastapi
Requires-Dist: firebase-admin
Requires-Dist: google
Requires-Dist: pydantic
